backend/sim/rtl/i2c_slave.v
`timescale 1ns / 1ps

module i2c_slave (
    input wire clk,   // 系統時鐘
    input wire rst_n, // 非同步 reset（active low）

    // 配置
    input wire [6:0] slave_addr,  // 本 slave 的 7-bit address

    // 狀態輸出
    output reg       busy,          // transaction 進行中
    output reg [7:0] reg_addr,      // 目前操作的 register address
    output reg [7:0] reg_data_out,  // 最近一次寫入的 data（debug 用）
    output reg       write_valid,   // 有新資料被寫入 register（one-cycle pulse）

    // I2C bus
    input wire scl,  // I2C clock（由 Master 驅動）
    inout wire sda   // I2C data（open-drain, bidirectional）
);
    reg [7:0] register_file[0:255];  // 256 個 8-bit register
    reg [7:0] slave_addr_recive;
    reg [7:0] shift_reg;           // 接收中的 byte 暫存器
    reg sda_oe;
    reg [3:0] bit_cnt;
    reg first_byte_received;
    reg sda_prev, scl_prev;  // 用來檢測 SDA 和 SCL 的邊緣

    //// Start 和 Stop 條件的檢測////////
    wire start_condition = scl & sda_prev & ~sda;
    // Guard stop_condition: during READ-ACK the master releases SDA (0→1) while
    // SCL is still high, which looks like a STOP but is not.  Suppress
    // detection during the READ-ACK window tracked by in_read_ack_window.
    wire stop_condition = scl & ~sda_prev & sda & ~in_read_ack_window;

    //// scl ///
    wire scl_rising = (scl_prev == 0) && (scl == 1);
    wire scl_falling = (scl_prev == 1) && (scl == 0);

    //// open-drain 控制 SDA 線 ////
    assign sda = sda_oe ? 1'b0 : 1'bz;

    reg [2:0] state;
    reg [2:0] ack_state;
    // idle addr ack read write
    localparam IDLE = 3'b000, ADDR = 3'b001, ACK = 3'b010, READ = 3'b011, WRITE = 3'b100;

    // One-cycle flag set while slave is in ACK state with ack_state == READ
    // (master byte ACK) or on the immediately following cycle (state == READ).
    // Used to suppress false stop_condition detection when the master releases
    // SDA during READ-mode ACK while SCL is still high.
    reg in_read_ack_window;

    always @(posedge clk or negedge rst_n) begin
        if (!rst_n) begin
            busy <= 0;
            reg_addr <= 0;
            reg_data_out <= 0;
            slave_addr_recive <= 0;
            shift_reg <= 0;
            write_valid <= 0;
            sda_oe <= 0;

            bit_cnt <= 0;
            sda_prev <= 1;
            scl_prev <= 1;
            state <= IDLE;
            in_read_ack_window <= 0;
        end else begin
            sda_prev <= sda;
            scl_prev <= scl;
                    // Suppress false STOP detection while the slave is transmitting
            // read data (READ state) or during the ACK phase following a read
            // byte (ACK state with ack_state==READ).
            //
            // In READ mode the master legitimately releases SDA (driving it
            // from 0 to 1) while SCL is high at the start of each inter-byte
            // ACK window.  The slave must not interpret this as a STOP; it
            // detects end-of-read via the NACK signal (SDA high at scl_rising
            // in ACK state) rather than via the stop_condition wire.
            //
            // A genuine STOP issued by the master after a NACK will be
            // detected once the slave transitions to IDLE state, at which
            // point in_read_ack_window is 0 and stop_condition is unmasked.
            in_read_ack_window <= (state == READ) ||
                                  (state == ACK && ack_state == READ);
            if (stop_condition) begin
                busy   <= 0;
                sda_oe <= 0;
                state  <= IDLE;
            end else if (start_condition) begin
                busy <= 1;
                state <= ADDR;
                bit_cnt <= 0;
                sda_oe <= 0;
            end
            case (state)
                IDLE: begin
                    bit_cnt <= 0;
                end

                ADDR: begin
                    if (scl_rising) begin  // 在 SCL 上升沿讀取 SDA
                        bit_cnt <= bit_cnt + 1;
                        slave_addr_recive <= {
                            slave_addr_recive[6:0], sda
                        };  // Shift in address bits
                    end else if (scl_falling) begin
                        if (bit_cnt == 8) begin
                            if (slave_addr_recive[7:1] == slave_addr) begin
                                state <= ACK;
                                ack_state <= ADDR;
                                sda_oe <= 1;  // ACK
                            end else begin
                                state  <= IDLE;  // Address 不匹配，回到 IDLE
                                sda_oe <= 0;
                            end
                        end
                    end
                end

                ACK: begin
                    bit_cnt <= 0;
                    case (ack_state)
                        ADDR: begin
                            if (scl_falling) begin
                                sda_oe <= 0;
                                if (slave_addr_recive[0]) begin
                                    state <= READ;  // Master 要讀取資料
                                    sda_oe <= ~register_file[reg_addr][7];  // 先準備好第一個 bit
                                end else begin
                                    state <= WRITE;  // Master 要寫入資料
                                    first_byte_received <= 0;
                                end
                            end
                        end
                        READ: begin
                            if (scl_rising) begin
                                if (sda) begin
                                    state <= IDLE;
                                end else begin
                                    reg_addr <= reg_addr + 1;
                                    sda_oe <= ~register_file[reg_addr][7];  // 先準備好第一個 bit
                                    state <= READ;
                                end
                            end
                        end
                        WRITE: begin
                            write_valid <= 0;
                            if (scl_falling) begin
                                sda_oe <= 0;
                                if (first_byte_received) begin
                                    reg_addr <= reg_addr + 1;
                                end else begin
                                    first_byte_received <= 1;
                                end
                                state <= WRITE;
                            end
                        end
                        default: state <= IDLE;
                    endcase
                end
                READ: begin
                    if (scl_rising) begin
                        bit_cnt <= bit_cnt + 1;
                    end else if (scl_falling) begin
                        if (bit_cnt == 8) begin
                            sda_oe <= 0;
                            state <= ACK;
                            ack_state <= READ;
                        end else begin
                            sda_oe <= ~register_file[reg_addr][7-bit_cnt];
                        end
                    end
                end
                WRITE: begin
                    if (scl_rising) begin
                        bit_cnt <= bit_cnt + 1;
                        shift_reg <= {shift_reg[6:0], sda};
                    end else if (scl_falling) begin
                        if (bit_cnt == 8) begin
                            if (first_byte_received) begin
                                register_file[reg_addr] <= shift_reg;
                                reg_data_out <= shift_reg;
                            end else begin
                                reg_addr <= shift_reg;
                            end
                            write_valid <= first_byte_received;
                            sda_oe <= 1;
                            state <= ACK;
                            ack_state <= WRITE;
                        end
                    end
                end
                default: state <= IDLE;

            endcase
        end
    end
endmodule

backend/sim/rtl/i2c_master.v
`timescale 1ns / 1ps
module i2c_master (
    input wire clk,   // 系統時鐘
    input wire rst_n, // 非同步 reset（active low）

    // Transaction 控制
    input wire       start,          // 觸發一筆 transaction
    input wire       rw,             // 0 = write, 1 = read
    input wire [6:0] slave_addr,     // 7-bit slave address
    input wire [7:0] data_in,        // 寫入用的 data（write mode）
    input wire [3:0] num_bytes,      // 本次 transaction 要傳輸的 byte 數（1~15）
    input wire       repeated_start, // 1 = transaction 結束時送 repeated start 而非 STOP

    // 狀態輸出
    output reg busy,  // transaction 進行中
    output reg done,  // transaction 完成（one-cycle pulse）
    output reg ack_error,  // slave 回 NACK
    output reg [7:0] data_out,  // 讀取到的 data（read mode，每 byte 有效時更新）
    output reg data_valid,   // data_out 有效（one-cycle pulse，每讀完一個 byte 拉高一次）
    output reg [3:0] byte_count,  // 目前已傳輸的 byte 數

    // I2C bus
    output wire scl,  // I2C clock（open-drain）
    inout  wire sda   // I2C data（open-drain, bidirectional）
);

  // parameter / 內部 reg、wire 宣告
  parameter integer CLK_DIV = 100;

  localparam integer N_EDGE = 0,
                     LOW_MID = CLK_DIV / 4,
                     P_EDGE = CLK_DIV / 2,
                     HIGH_MID = 3 * CLK_DIV / 4;

  localparam integer IDLE           = 3'b000,
                     START          = 3'b001,
                     ADDR           = 3'b010,
                     WRITE          = 3'b011,
                     READ           = 3'b100,
                     ACK            = 3'b101,
                     REPEATED_START = 3'b110,
                     STOP           = 3'b111;

  reg [$clog2(CLK_DIV)-1:0] clk_div_cnt;  // clock divider counter
  reg sda_oe;
  reg scl_oe;

  reg [2:0] state;
  reg [7:0] addr_buf;
  reg [7:0] data_buf;
  reg [2:0] bit_cnt;
  reg [2:0] ack_flag;

  // clock divider counter 的 always block
  always @(posedge clk or negedge rst_n) begin
    if (!rst_n) begin
      clk_div_cnt <= 0;
    end else if (clk_div_cnt == CLK_DIV - 1) begin
      clk_div_cnt <= 0;
    end else begin
      clk_div_cnt <= clk_div_cnt + 1;
    end
  end

  // open-drain
  assign sda = sda_oe ? 1'b0 : 1'bz;  // sda_oe = 1 時拉低，否則高阻
  assign scl = scl_oe ? 1'b0 : 1'bz;  //

  // scl
  always @(posedge clk or negedge rst_n) begin
    if (!rst_n) begin
      scl_oe <= 0;
    end else begin
      case (state)
        IDLE, START: scl_oe <= 0;  // IDLE 和 START 狀態保持 SCL 高阻
        // STOP 使用 default 正常 clock，讓 slave 有 scl_falling 釋放 ACK
        default: begin
          if (clk_div_cnt < P_EDGE) begin
            scl_oe <= 1;  // 前半週期拉低 SCL
          end else begin
            scl_oe <= 0;  // 後半週期釋放 SCL
          end
        end
      endcase
    end
  end


  // FSM state transition 的 always block
  always @(posedge clk or negedge rst_n) begin
    if (!rst_n) begin
      sda_oe <= 0;
      busy <= 0;
      done <= 0;
      ack_error <= 0;
      data_valid <= 0;
      data_buf <= 0;
      data_out <= 0;
      addr_buf <= 0;
      byte_count <= 0;
      bit_cnt <= 0;
      state <= IDLE;
    end else begin
      done <= 0;
      data_valid <= 0;
      case (state)
        IDLE: begin
          sda_oe <= 0;
          busy   <= 0;
          done   <= 0;
          if (start) begin
            state <= START;
            ack_error <= 0;
            busy <= 1;
          end
        end
        START: begin
          bit_cnt <= 0;
          byte_count <= 0;
          if (clk_div_cnt == HIGH_MID) begin
            sda_oe <= 1;  // 拉低 SDA 產生 start condition
            addr_buf <= {slave_addr, rw};  // 7-bit address + write bit (0)
            state <= ADDR;
          end
        end
        ADDR: begin
          case (clk_div_cnt)
            LOW_MID: sda_oe <= ~addr_buf[7-bit_cnt];  // MSB first
            HIGH_MID: begin
              if (bit_cnt == 7) begin
                ack_flag <= ADDR;
                state <= ACK;
              end
              bit_cnt <= bit_cnt + 1;
            end
            default: begin
              sda_oe <= sda_oe;
            end
          endcase
        end
        WRITE: begin
          case (clk_div_cnt)
            LOW_MID: sda_oe <= ~data_buf[7-bit_cnt];  // MSB first
            HIGH_MID: begin
              if (bit_cnt == 7) begin
                ack_flag <= WRITE;
                state <= ACK;  // 發送完 data 後進入 ACK phase
                // sda_oe 由 ACK state 的 LOW_MID 釋放，避免在 SCL HIGH 時產生假 STOP
              end
              bit_cnt <= bit_cnt + 1;
            end
            default: begin
              sda_oe <= sda_oe;
            end
          endcase
        end
        READ: begin
          case (clk_div_cnt)
            HIGH_MID: begin
              if (bit_cnt == 7) begin
                ack_flag <= READ;
                data_valid <= 1;
                data_out <= {data_buf[6:0], sda};  // 更新 data_out
                state <= ACK;  // 讀取完一個 byte 後進入 ACK phase
              end
              data_buf <= {data_buf[6:0], sda};  // MSB first
              bit_cnt  <= bit_cnt + 1;
            end
            default: begin
              data_out   <= data_out;
              data_valid <= 0;
            end
          endcase
        end
        ACK: begin
          case (clk_div_cnt)
            LOW_MID: begin
              case (ack_flag)
                ADDR, WRITE: sda_oe <= 0;  // 釋放 SDA 等待 slave 回 ACK/NACK
                READ: begin
                  if (byte_count == num_bytes - 1) begin
                    sda_oe <= 0;  // 其他情況釋放 SDA 等待 slave 回 ACK/NACK
                  end else begin
                    sda_oe <= 1;  // 最後一個 byte 讀取完後拉低 SDA 送 NACK
                  end
                end
                default: sda_oe <= sda_oe;
              endcase
            end
            HIGH_MID: begin
              case (ack_flag)
                ADDR: begin  // address phase 不更新 data_out
                  if (sda) begin
                    ack_error <= 1;  // NACK
                    state <= STOP;  // 發生 NACK 就結束 transaction
                  end else begin
                    if (rw) begin
                      state <= READ;
                    end else begin
                      data_buf <= data_in;
                      state <= WRITE;
                    end
                  end
                end
                WRITE: begin
                  if (sda) begin
                    ack_error <= 1;  // NACK
                  end
                  byte_count <= byte_count + 1;
                  if (byte_count == num_bytes - 1) begin
                    if (repeated_start) begin
                      state <= REPEATED_START;
                    end else begin
                      state <= STOP;
                    end
                  end else begin
                    data_buf <= data_in;
                    state <= WRITE;
                  end
                end
                READ: begin
                  data_valid <= 0;
                  byte_count <= byte_count + 1;
                  sda_oe <= 0;
                  if (byte_count == num_bytes - 1) begin
                    sda_oe <= 1;  // 最後一個 byte 讀取完後送 NACK
                    if (repeated_start) begin
                      state <= REPEATED_START;
                    end else begin
                      state <= STOP;
                    end
                  end else begin
                    state <= READ;
                  end
                end
                default: state <= state;
              endcase
            end
            default: begin
              sda_oe <= sda_oe;
            end
          endcase
          bit_cnt <= 0;
        end
        STOP: begin
          case (clk_div_cnt)
            LOW_MID: sda_oe <= 1;  // 拉低 SDA
            HIGH_MID: begin
              sda_oe <= 0;  // 釋放 SDA 產生 stop condition
              done   <= 1;
              state  <= IDLE;
            end
            default: begin
              sda_oe <= sda_oe;
            end
          endcase
        end
        REPEATED_START: begin
          case (clk_div_cnt)
            LOW_MID: sda_oe <= 0;  // 釋放 SDA 產生 stop condition
            HIGH_MID: begin
              sda_oe <= 1;  // 拉低 SDA 產生 start condition
              addr_buf <= {slave_addr, rw};  // 7-bit address + write bit
              bit_cnt <= 0;
              byte_count <= 0;
              state <= ADDR;
            end
            default: begin
              sda_oe <= sda_oe;
            end
          endcase
        end
        default: state <= state;
      endcase
    end
  end
endmodule

backend/sim/rtl/i2c_top.v
`timescale 1ns / 1ps

// I2C 系統頂層模組 — 連接 master + slave + bus
module i2c_top #(
    parameter CLK_DIV = 100
) (
    // 系統
    input wire clk,
    input wire rst_n,

    // Master 控制信號
    input wire       start,
    input wire       rw,
    input wire [6:0] slave_addr,
    input wire [7:0] data_in,
    input wire [3:0] num_bytes,
    input wire       repeated_start,

    // Slave 設定
    input wire [6:0] slave_addr_cfg,

    // Master 狀態輸出
    output wire       busy,
    output wire       done,
    output wire       ack_error,
    output wire [7:0] data_out,
    output wire       data_valid,
    output wire [3:0] byte_count,

    // Slave 狀態輸出
    output wire       slave_busy,
    output wire [7:0] reg_addr,
    output wire [7:0] reg_data_out,
    output wire       write_valid
);

    // I2C bus 線路
    wire sda;
    wire scl;

    // Pullup 電阻（模擬 open-drain bus）
    pullup (sda);
    pullup (scl);

    // Master instance
    i2c_master #(
        .CLK_DIV(CLK_DIV)
    ) master_inst (
        .clk      (clk),
        .rst_n    (rst_n),
        .start    (start),
        .rw       (rw),
        .slave_addr(slave_addr),
        .data_in  (data_in),
        .num_bytes(num_bytes),
        .repeated_start(repeated_start),
        .busy     (busy),
        .done     (done),
        .ack_error(ack_error),
        .data_out (data_out),
        .data_valid(data_valid),
        .byte_count(byte_count),
        .scl      (scl),
        .sda      (sda)
    );

    // Slave instance
    i2c_slave slave_inst (
        .clk      (clk),
        .rst_n    (rst_n),
        .slave_addr(slave_addr_cfg),
        .busy     (slave_busy),
        .reg_addr (reg_addr),
        .reg_data_out(reg_data_out),
        .write_valid(write_valid),
        .scl      (scl),
        .sda      (sda)
    );

endmodule

backend/sim/tb/i2c_system_wrapper.v
`timescale 1ns / 1ps
// cocotb wrapper for i2c_top (system-level test)
module i2c_system_wrapper;

    parameter CLK_DIV = 50;
    parameter SLAVE_ADDR = 7'h50;

    reg        clk, rst_n;
    reg        start, rw;
    reg  [6:0] slave_addr_in;
    reg  [7:0] data_in;
    reg  [3:0] num_bytes;
    reg        repeated_start_in;
    reg  [6:0] slave_addr_cfg;

    wire       busy, done, ack_error;
    wire [7:0] data_out;
    wire       data_valid;
    wire [3:0] byte_count;
    wire       slave_busy;
    wire [7:0] reg_addr;
    wire [7:0] reg_data_out;
    wire       write_valid;

    i2c_top #(.CLK_DIV(CLK_DIV)) dut (
        .clk           (clk),
        .rst_n         (rst_n),
        .start         (start),
        .rw            (rw),
        .slave_addr    (slave_addr_in),
        .data_in       (data_in),
        .num_bytes     (num_bytes),
        .repeated_start(repeated_start_in),
        .slave_addr_cfg(slave_addr_cfg),
        .busy          (busy),
        .done          (done),
        .ack_error     (ack_error),
        .data_out      (data_out),
        .data_valid    (data_valid),
        .byte_count    (byte_count),
        .slave_busy    (slave_busy),
        .reg_addr      (reg_addr),
        .reg_data_out  (reg_data_out),
        .write_valid   (write_valid)
    );

    // Clock is driven by cocotb (Clock generator) so this wrapper is
    // compatible with both event-driven (Icarus) and cycle-based (Verilator)
    // simulators.  No Verilog #delay clock generation here.

    // VCD dump — only for Icarus; Verilator uses --trace at build time.
`ifndef VERILATOR
    initial begin
        $dumpfile("i2c_system_cocotb.vcd");
        $dumpvars(0, i2c_system_wrapper);
    end
`endif

endmodule

backend/sim/tests/i2c_system_cocotb.vcd
$date
	Sat Mar  7 22:00:05 2026
$end
$version
	Icarus Verilog
$end
$timescale
	1ps
$end
$scope module i2c_system_wrapper $end
$var wire 1 ! write_valid $end
$var wire 1 " slave_busy $end
$var wire 8 # reg_data_out [7:0] $end
$var wire 8 $ reg_addr [7:0] $end
$var wire 1 % done $end
$var wire 1 & data_valid $end
$var wire 8 ' data_out [7:0] $end
$var wire 4 ( byte_count [3:0] $end
$var wire 1 ) busy $end
$var wire 1 * ack_error $end
$var parameter 32 + CLK_DIV $end
$var parameter 7 , SLAVE_ADDR $end
$var reg 1 - clk $end
$var reg 8 . data_in [7:0] $end
$var reg 4 / num_bytes [3:0] $end
$var reg 1 0 repeated_start_in $end
$var reg 1 1 rst_n $end
$var reg 1 2 rw $end
$var reg 7 3 slave_addr_cfg [6:0] $end
$var reg 7 4 slave_addr_in [6:0] $end
$var reg 1 5 start $end
$scope module dut $end
$var wire 1 - clk $end
$var wire 8 6 data_in [7:0] $end
$var wire 4 7 num_bytes [3:0] $end
$var wire 1 0 repeated_start $end
$var wire 1 1 rst_n $end
$var wire 1 2 rw $end
$var wire 1 8 scl $end
$var wire 1 9 sda $end
$var wire 7 : slave_addr [6:0] $end
$var wire 7 ; slave_addr_cfg [6:0] $end
$var wire 1 5 start $end
$var wire 1 ! write_valid $end
$var wire 1 " slave_busy $end
$var wire 8 < reg_data_out [7:0] $end
$var wire 8 = reg_addr [7:0] $end
$var wire 1 % done $end
$var wire 1 & data_valid $end
$var wire 8 > data_out [7:0] $end
$var wire 4 ? byte_count [3:0] $end
$var wire 1 ) busy $end
$var wire 1 * ack_error $end
$var parameter 32 @ CLK_DIV $end
$scope module master_inst $end
$var wire 1 - clk $end
$var wire 8 A data_in [7:0] $end
$var wire 4 B num_bytes [3:0] $end
$var wire 1 0 repeated_start $end
$var wire 1 1 rst_n $end
$var wire 1 2 rw $end
$var wire 1 8 scl $end
$var wire 1 9 sda $end
$var wire 7 C slave_addr [6:0] $end
$var wire 1 5 start $end
$var parameter 32 D ACK $end
$var parameter 32 E ADDR $end
$var parameter 32 F CLK_DIV $end
$var parameter 32 G HIGH_MID $end
$var parameter 32 H IDLE $end
$var parameter 32 I LOW_MID $end
$var parameter 32 J N_EDGE $end
$var parameter 32 K P_EDGE $end
$var parameter 32 L READ $end
$var parameter 32 M REPEATED_START $end
$var parameter 32 N START $end
$var parameter 32 O STOP $end
$var parameter 32 P WRITE $end
$var reg 1 * ack_error $end
$var reg 3 Q ack_flag [2:0] $end
$var reg 8 R addr_buf [7:0] $end
$var reg 3 S bit_cnt [2:0] $end
$var reg 1 ) busy $end
$var reg 4 T byte_count [3:0] $end
$var reg 6 U clk_div_cnt [5:0] $end
$var reg 8 V data_buf [7:0] $end
$var reg 8 W data_out [7:0] $end
$var reg 1 & data_valid $end
$var reg 1 % done $end
$var reg 1 X scl_oe $end
$var reg 1 Y sda_oe $end
$var reg 3 Z state [2:0] $end
$upscope $end
$scope module slave_inst $end
$var wire 1 - clk $end
$var wire 1 1 rst_n $end
$var wire 1 8 scl $end
$var wire 1 [ scl_falling $end
$var wire 1 \ scl_rising $end
$var wire 1 9 sda $end
$var wire 7 ] slave_addr [6:0] $end
$var wire 1 ^ start_condition $end
$var wire 1 _ stop_condition $end
$var parameter 3 ` ACK $end
$var parameter 3 a ADDR $end
$var parameter 3 b IDLE $end
$var parameter 3 c READ $end
$var parameter 3 d WRITE $end
$var reg 3 e ack_state [2:0] $end
$var reg 4 f bit_cnt [3:0] $end
$var reg 1 " busy $end
$var reg 1 g first_byte_received $end
$var reg 1 h in_read_ack_window $end
$var reg 8 i reg_addr [7:0] $end
$var reg 8 j reg_data_out [7:0] $end
$var reg 1 k scl_prev $end
$var reg 1 l sda_oe $end
$var reg 1 m sda_prev $end
$var reg 8 n shift_reg [7:0] $end
$var reg 8 o slave_addr_recive [7:0] $end
$var reg 3 p state [2:0] $end
$var reg 1 ! write_valid $end
$upscope $end
$upscope $end
$upscope $end
$enddefinitions $end
$comment Show the parameter values. $end
$dumpall
b100 d
b11 c
b0 b
b1 a
b10 `
b11 P
b111 O
b1 N
b110 M
b100 L
b11001 K
b0 J
b1100 I
b0 H
b100101 G
b110010 F
b10 E
b101 D
b110010 @
b1010000 ,
b110010 +
$end
#0
$dumpvars
b0 p
b0 o
b0 n
1m
0l
1k
b0 j
b0 i
0h
xg
b0 f
bx e
0_
0^
b1010000 ]
0\
0[
b0 Z
0Y
0X
b0 W
b0 V
b0 U
b0 T
b0 S
b0 R
bx Q
b0 C
b0 B
b0 A
b0 ?
b0 >
b0 =
b0 <
b1010000 ;
b0 :
19
18
b0 7
b0 6
05
b0 4
b1010000 3
02
01
00
b0 /
b0 .
0-
0*
0)
b0 (
b0 '
0&
0%
b0 $
b0 #
0"
0!
$end
#5000
1-
#10000
0-
#15000
1-
#20000
0-
#25000
1-
#30000
0-
#35000
1-
#40000
0-
#45000
11
1-
#50000
0-
#55000
b1 U
1-
#60000
0-
#65000
b10 U
1-
#70000
0-
#75000
b11 U
1-
#80000
0-
#85000
b100 U
1-
#90000
0-
#95000
15
b10000 .
b10000 6
b10000 A
b10 /
b10 7
b10 B
b1010000 4
b1010000 :
b1010000 C
b101 U
1-
#100000
0-
#105000
05
1)
b1 Z
b110 U
1-
#110000
0-
#115000
b111 U
1-
#120000
0-
#125000
b1000 U
1-
#130000
0-
#135000
b1001 U
1-
#140000
0-
#145000
b1010 U
1-
#150000
0-
#155000
b1011 U
1-
#160000
0-
#165000
b1100 U
1-
#170000
0-
#175000
b1101 U
1-
#180000
0-
#185000
b1110 U
1-
#190000
0-
#195000
b1111 U
1-
#200000
0-
#205000
b10000 U
1-
#210000
0-
#215000
b10001 U
1-
#220000
0-
#225000
b10010 U
1-
#230000
0-
#235000
b10011 U
1-
#240000
0-
#245000
b10100 U
1-
#250000
0-
#255000
b10101 U
1-
#260000
0-
#265000
b10110 U
1-
#270000
0-
#275000
b10111 U
1-
#280000
0-
#285000
b11000 U
1-
#290000
0-
#295000
b11001 U
1-
#300000
0-
#305000
b11010 U
1-
#310000
0-
#315000
b11011 U
1-
#320000
0-
#325000
b11100 U
1-
#330000
0-
#335000
b11101 U
1-
#340000
0-
#345000
b11110 U
1-
#350000
0-
#355000
b11111 U
1-
#360000
0-
#365000
b100000 U
1-
#370000
0-
#375000
b100001 U
1-
#380000
0-
#385000
b100010 U
1-
#390000
0-
#395000
b100011 U
1-
#400000
0-
#405000
b100100 U
1-
#410000
0-
#415000
b100101 U
1-
#420000
0-
#425000
1^
09
b10 Z
b10100000 R
1Y
b100110 U
1-
#430000
0-
#435000
0^
b100111 U
b1 p
1"
0m
1-
#440000
0-
#445000
b101000 U
1-
#450000
0-
#455000
b101001 U
1-
#460000
0-
#465000
b101010 U
1-
#470000
0-
#475000
b101011 U
1-
#480000
0-
#485000
b101100 U
1-
#490000
0-
#495000
b101101 U
1-
#500000
0-
#505000
b101110 U
1-
#510000
0-
#515000
b101111 U
1-
#520000
0-
#525000
b110000 U
1-
#530000
0-
#535000
b110001 U
1-
#540000
0-
#545000
b0 U
1-
#550000
0-
#555000
1[
08
b1 U
1X
1-
#560000
0-
#565000
0[
0k
b10 U
1-
#570000
0-
#575000
b11 U
1-
#580000
0-
#585000
b100 U
1-
#590000
0-
#595000
b101 U
1-
#600000
0-
#605000
b110 U
1-
#610000
0-
#615000
b111 U
1-
#620000
0-
#625000
b1000 U
1-
#630000
0-
#635000
b1001 U
1-
#640000
0-
#645000
b1010 U
1-
#650000
0-
#655000
b1011 U
1-
#660000
0-
#665000
b1100 U
1-
#670000
0-
#675000
19
b1101 U
0Y
1-
#680000
0-
#685000
1m
b1110 U
1-
#690000
0-
#695000
b1111 U
1-
#700000
0-
#705000
b10000 U
1-
#710000
0-
#715000
b10001 U
1-
#720000
0-
#725000
b10010 U
1-
#730000
0-
#735000
b10011 U
1-
#740000
0-
#745000
b10100 U
1-
#750000
0-
#755000
b10101 U
1-
#760000
0-
#765000
b10110 U
1-
#770000
0-
#775000
b10111 U
1-
#780000
0-
#785000
b11000 U
1-
#790000
0-
#795000
b11001 U
1-
#800000
0-
#805000
1\
18
0X
b11010 U
1-
#810000
0-
#815000
0\
b11011 U
b1 o
b1 f
1k
1-
#820000
0-
#825000
b11100 U
1-
#830000
0-
#835000
b11101 U
1-
#840000
0-
#845000
b11110 U
1-
#850000
0-
#855000
b11111 U
1-
#860000
0-
#865000
b100000 U
1-
#870000
0-
#875000
b100001 U
1-
#880000
0-
#885000
b100010 U
1-
#890000
0-
#895000
b100011 U
1-
#900000
0-
#905000
b100100 U
1-
#910000
0-
#915000
b100101 U
1-
#920000
0-
#925000
b1 S
b100110 U
1-
#930000
0-
#935000
b100111 U
1-
#940000
0-
#945000
b101000 U
1-
#950000
0-
#955000
b101001 U
1-
#960000
0-
#965000
b101010 U
1-
#970000
0-
#975000
b101011 U
1-
#980000
0-
#985000
b101100 U
1-
#990000
0-
#995000
b101101 U
1-
#1000000
0-
#1005000
b101110 U
1-
#1010000
0-
#1015000
b101111 U
1-
#1020000
0-
#1025000
b110000 U
1-
#1030000
0-
#1035000
b110001 U
1-
#1040000
0-
#1045000
b0 U
1-
#1050000
0-
#1055000
1[
08
b1 U
1X
1-
#1060000
0-
#1065000
0[
0k
b10 U
1-
#1070000
0-
#1075000
b11 U
1-
#1080000
0-
#1085000
b100 U
1-
#1090000
0-
#1095000
b101 U
1-
#1100000
0-
#1105000
b110 U
1-
#1110000
0-
#1115000
b111 U
1-
#1120000
0-
#1125000
b1000 U
1-
#1130000
0-
#1135000
b1001 U
1-
#1140000
0-
#1145000
b1010 U
1-
#1150000
0-
#1155000
b1011 U
1-
#1160000
0-
#1165000
b1100 U
1-
#1170000
0-
#1175000
09
b1101 U
1Y
1-
#1180000
0-
#1185000
0m
b1110 U
1-
#1190000
0-
#1195000
b1111 U
1-
#1200000
0-
#1205000
b10000 U
1-
#1210000
0-
#1215000
b10001 U
1-
#1220000
0-
#1225000
b10010 U
1-
#1230000
0-
#1235000
b10011 U
1-
#1240000
0-
#1245000
b10100 U
1-
#1250000
0-
#1255000
b10101 U
1-
#1260000
0-
#1265000
b10110 U
1-
#1270000
0-
#1275000
b10111 U
1-
#1280000
0-
#1285000
b11000 U
1-
#1290000
0-
#1295000
b11001 U
1-
#1300000
0-
#1305000
1\
18
0X
b11010 U
1-
#1310000
0-
#1315000
0\
b11011 U
b10 o
b10 f
1k
1-
#1320000
0-
#1325000
b11100 U
1-
#1330000
0-
#1335000
b11101 U
1-
#1340000
0-
#1345000
b11110 U
1-
#1350000
0-
#1355000
b11111 U
1-
#1360000
0-
#1365000
b100000 U
1-
#1370000
0-
#1375000
b100001 U
1-
#1380000
0-
#1385000
b100010 U
1-
#1390000
0-
#1395000
b100011 U
1-
#1400000
0-
#1405000
b100100 U
1-
#1410000
0-
#1415000
b100101 U
1-
#1420000
0-
#1425000
b10 S
b100110 U
1-
#1430000
0-
#1435000
b100111 U
1-
#1440000
0-
#1445000
b101000 U
1-
#1450000
0-
#1455000
b101001 U
1-
#1460000
0-
#1465000
b101010 U
1-
#1470000
0-
#1475000
b101011 U
1-
#1480000
0-
#1485000
b101100 U
1-
#1490000
0-
#1495000
b101101 U
1-
#1500000
0-
#1505000
b101110 U
1-
#1510000
0-
#1515000
b101111 U
1-
#1520000
0-
#1525000
b110000 U
1-
#1530000
0-
#1535000
b110001 U
1-
#1540000
0-
#1545000
b0 U
1-
#1550000
0-
#1555000
1[
08
b1 U
1X
1-
#1560000
0-
#1565000
0[
0k
b10 U
1-
#1570000
0-
#1575000
b11 U
1-
#1580000
0-
#1585000
b100 U
1-
#1590000
0-
#1595000
b101 U
1-
#1600000
0-
#1605000
b110 U
1-
#1610000
0-
#1615000
b111 U
1-
#1620000
0-
#1625000
b1000 U
1-
#1630000
0-
#1635000
b1001 U
1-
#1640000
0-
#1645000
b1010 U
1-
#1650000
0-
#1655000
b1011 U
1-
#1660000
0-
#1665000
b1100 U
1-
#1670000
0-
#1675000
19
b1101 U
0Y
1-
#1680000
0-
#1685000
1m
b1110 U
1-
#1690000
0-
#1695000
b1111 U
1-
#1700000
0-
#1705000
b10000 U
1-
#1710000
0-
#1715000
b10001 U
1-
#1720000
0-
#1725000
b10010 U
1-
#1730000
0-
#1735000
b10011 U
1-
#1740000
0-
#1745000
b10100 U
1-
#1750000
0-
#1755000
b10101 U
1-
#1760000
0-
#1765000
b10110 U
1-
#1770000
0-
#1775000
b10111 U
1-
#1780000
0-
#1785000
b11000 U
1-
#1790000
0-
#1795000
b11001 U
1-
#1800000
0-
#1805000
1\
18
0X
b11010 U
1-
#1810000
0-
#1815000
0\
b11011 U
b101 o
b11 f
1k
1-
#1820000
0-
#1825000
b11100 U
1-
#1830000
0-
#1835000
b11101 U
1-
#1840000
0-
#1845000
b11110 U
1-
#1850000
0-
#1855000
b11111 U
1-
#1860000
0-
#1865000
b100000 U
1-
#1870000
0-
#1875000
b100001 U
1-
#1880000
0-
#1885000
b100010 U
1-
#1890000
0-
#1895000
b100011 U
1-
#1900000
0-
#1905000
b100100 U
1-
#1910000
0-
#1915000
b100101 U
1-
#1920000
0-
#1925000
b11 S
b100110 U
1-
#1930000
0-
#1935000
b100111 U
1-
#1940000
0-
#1945000
b101000 U
1-
#1950000
0-
#1955000
b101001 U
1-
#1960000
0-
#1965000
b101010 U
1-
#1970000
0-
#1975000
b101011 U
1-
#1980000
0-
#1985000
b101100 U
1-
#1990000
0-
#1995000
b101101 U
1-
#2000000
0-
#2005000
b101110 U
1-
#2010000
0-
#2015000
b101111 U
1-
#2020000
0-
#2025000
b110000 U
1-
#2030000
0-
#2035000
b110001 U
1-
#2040000
0-
#2045000
b0 U
1-
#2050000
0-
#2055000
1[
08
b1 U
1X
1-
#2060000
0-
#2065000
0[
0k
b10 U
1-
#2070000
0-
#2075000
b11 U
1-
